rempy/__init__.py
rempy/main.py
rempy/runtime/__init__.py
rempy/runtime/remote_cli.py
rempy/sync/__init__.py
rempy/sync/manager.py
rempy/sync/patcher.py
tests/__init__.py
tests/hello.py
rempy-2.2.0.dist-info/LICENSE
rempy-2.2.0.dist-info/METADATA
rempy-2.2.0.dist-info/WHEEL
rempy-2.2.0.dist-info/entry_points.txt
rempy-2.2.0.dist-info/top_level.txt
rempy-2.2.0.dist-info/RECORD
