Metadata-Version: 2.1
Name: rempy
Version: 2.2.0
Summary: Execute python scripts, modules or entire projects on a remote server.
Home-page: https://github.com/penguinmenac3/rempy
Download-URL: https://github.com/penguinmenac3/rempy/tarball/2.2.0
Author: Michael Fuerst
Author-email: mail@michaelfuerst.de
License: BSD
Classifier: Development Status :: 3 - Alpha
Classifier: Intended Audience :: Developers
Classifier: Programming Language :: Python
License-File: LICENSE
Requires-Dist: pexpect
